CHANGELOG.txt
LICENSE.txt
MANIFEST.in
README.md
setup.py
python2pseudocode/__init__.py
python2pseudocode.egg-info/PKG-INFO
python2pseudocode.egg-info/SOURCES.txt
python2pseudocode.egg-info/dependency_links.txt
python2pseudocode.egg-info/top_level.txt