Metadata-Version: 2.1
Name: python2pseudocode
Version: 0.0.2
Summary: Converting Python code snippets to Pseudocode effectively.
Home-page: UNKNOWN
Author: anonymouscoolguy
Author-email: <anonymouscoolguy05@gmail.com>
License: UNKNOWN
Keywords: pseudocode,python
Platform: UNKNOWN
Classifier: Development Status :: 1 - Planning
Classifier: Intended Audience :: Education
Classifier: Programming Language :: Python :: 3
Classifier: Operating System :: Unix
Classifier: Operating System :: MacOS :: MacOS X
Classifier: Operating System :: Microsoft :: Windows
License-File: LICENSE.txt
